makima2/__init__.py
makima2/helper/__init__.py
makima2/helper/operation.py
makima2/windows/__init__.py
makima2/windows/image_object.py
makima2/windows/ui_element.py
makima2/windows/call_win_api/__init__.py
makima2/windows/call_win_api/i_accessible_ex.py
makima2/windows/call_win_api/i_element.py
makima2/windows/call_win_api/i_keyboard.py
makima2/windows/call_win_api/i_mouse.py
makima2/windows/utils/__init__.py
makima2/windows/utils/common.py
makima2/windows/utils/find_ui_element.py
makima2/windows/utils/keyboard.py
makima2/windows/utils/mouse.py
makima2/windows/utils/stack.py
Makima2-0.0.8.dist-info/METADATA
Makima2-0.0.8.dist-info/WHEEL
Makima2-0.0.8.dist-info/top_level.txt
Makima2-0.0.8.dist-info/RECORD
