Metadata-Version: 2.1
Name: Makima2
Version: 0.0.8
Summary: A cross-platform desktop automated testing framework.
Home-page: https://github.com/letmeNo1/Makima
Author: hank.huang
Author-email: hank.huang550@gmail.com
Classifier: Programming Language :: Python :: 3
Classifier: License :: OSI Approved :: MIT License
Classifier: Operating System :: OS Independent
Requires-Python: >=3.6
Requires-Dist: comtypes (==1.1.13)
Requires-Dist: numpy (>=1.21.0)
Requires-Dist: pyperclip (>=1.7.0)
